{
  "mainAssemblyName": "BlazorApp",
  "resources": {
    "hash": "sha256-nOFsDE/sLk1TC6J02xHP5C2GYth4sBr4BhKrd143Ob8=",
    "fingerprinting": {
      "BlazorApp.1d43lgvh6u.wasm": "BlazorApp.wasm",
      "Microsoft.AspNetCore.Components.n0yjlgty9j.wasm": "Microsoft.AspNetCore.Components.wasm",
      "Microsoft.AspNetCore.Components.Web.7apenvi18o.wasm": "Microsoft.AspNetCore.Components.Web.wasm",
      "Microsoft.AspNetCore.Components.WebAssembly.mhi741p0i5.wasm": "Microsoft.AspNetCore.Components.WebAssembly.wasm",
      "Microsoft.Extensions.Configuration.Abstractions.f9jq6u05xu.wasm": "Microsoft.Extensions.Configuration.Abstractions.wasm",
      "Microsoft.Extensions.Configuration.Json.77nptesqpn.wasm": "Microsoft.Extensions.Configuration.Json.wasm",
      "Microsoft.Extensions.Configuration.ell6o7ap7i.wasm": "Microsoft.Extensions.Configuration.wasm",
      "Microsoft.Extensions.DependencyInjection.Abstractions.ylgtpcauec.wasm": "Microsoft.Extensions.DependencyInjection.Abstractions.wasm",
      "Microsoft.Extensions.DependencyInjection.g8opmrm9gr.wasm": "Microsoft.Extensions.DependencyInjection.wasm",
      "Microsoft.Extensions.Logging.Abstractions.8cnp7o9mjf.wasm": "Microsoft.Extensions.Logging.Abstractions.wasm",
      "Microsoft.Extensions.Logging.5g1hnmwyc5.wasm": "Microsoft.Extensions.Logging.wasm",
      "Microsoft.Extensions.Options.9zsgy7ya5a.wasm": "Microsoft.Extensions.Options.wasm",
      "Microsoft.Extensions.Primitives.8omryeirak.wasm": "Microsoft.Extensions.Primitives.wasm",
      "Microsoft.JSInterop.426305nhc4.wasm": "Microsoft.JSInterop.wasm",
      "Microsoft.JSInterop.WebAssembly.heoad7mujs.wasm": "Microsoft.JSInterop.WebAssembly.wasm",
      "System.Collections.Concurrent.hsmjajo9fw.wasm": "System.Collections.Concurrent.wasm",
      "System.Collections.Immutable.ouzplzmqt8.wasm": "System.Collections.Immutable.wasm",
      "System.Collections.okewek4o8w.wasm": "System.Collections.wasm",
      "System.ComponentModel.Primitives.dwcl0i3ajf.wasm": "System.ComponentModel.Primitives.wasm",
      "System.ComponentModel.TypeConverter.fnfwo5xg84.wasm": "System.ComponentModel.TypeConverter.wasm",
      "System.ComponentModel.h9eo79o86x.wasm": "System.ComponentModel.wasm",
      "System.Console.ckimbfyjuj.wasm": "System.Console.wasm",
      "System.Diagnostics.DiagnosticSource.ubwvo3qscp.wasm": "System.Diagnostics.DiagnosticSource.wasm",
      "System.IO.Pipelines.h68d94scrb.wasm": "System.IO.Pipelines.wasm",
      "System.Linq.Expressions.qyb81d1kew.wasm": "System.Linq.Expressions.wasm",
      "System.Linq.Queryable.s5qq36zp1s.wasm": "System.Linq.Queryable.wasm",
      "System.Linq.m4r18hk5bi.wasm": "System.Linq.wasm",
      "System.Memory.acxyzgdz32.wasm": "System.Memory.wasm",
      "System.Net.Http.Json.9cqhqmryzt.wasm": "System.Net.Http.Json.wasm",
      "System.Net.Http.qsqlx2amef.wasm": "System.Net.Http.wasm",
      "System.Net.Primitives.3uow9zd1kc.wasm": "System.Net.Primitives.wasm",
      "System.ObjectModel.t8wvm8lr3b.wasm": "System.ObjectModel.wasm",
      "System.Private.CoreLib.34pfvi9gnz.wasm": "System.Private.CoreLib.wasm",
      "System.Private.Uri.nsfj740ux6.wasm": "System.Private.Uri.wasm",
      "System.Runtime.InteropServices.JavaScript.f4ln4hfftw.wasm": "System.Runtime.InteropServices.JavaScript.wasm",
      "System.Runtime.dx92bx8elt.wasm": "System.Runtime.wasm",
      "System.Text.Encodings.Web.4zpcd8unrt.wasm": "System.Text.Encodings.Web.wasm",
      "System.Text.Json.qgii1bka67.wasm": "System.Text.Json.wasm",
      "System.Text.RegularExpressions.0e9rlv7vxy.wasm": "System.Text.RegularExpressions.wasm",
      "System.v3da086c8u.wasm": "System.wasm",
      "dotnet.js": "dotnet.js",
      "dotnet.native.8bti36lthm.js": "dotnet.native.js",
      "dotnet.native.tr0cyonrwt.wasm": "dotnet.native.wasm",
      "dotnet.runtime.tsg4gsv2hg.js": "dotnet.runtime.js",
      "icudt_CJK.tjcz0u77k5.dat": "icudt_CJK.dat",
      "icudt_EFIGS.tptq2av103.dat": "icudt_EFIGS.dat",
      "icudt_no_CJK.lfu7j35m59.dat": "icudt_no_CJK.dat"
    },
    "jsModuleNative": {
      "dotnet.native.8bti36lthm.js": "sha256-HFADmT26AarHu4tMjFaTPxINmQjBJGtdPN+CKjtNMFE="
    },
    "jsModuleRuntime": {
      "dotnet.runtime.tsg4gsv2hg.js": "sha256-82FoDmY+LsehdN2u8aSGEutGEKXJHcYaSX/3zptbsCw="
    },
    "wasmNative": {
      "dotnet.native.tr0cyonrwt.wasm": "sha256-F3/BArijJUydqmwcdWeW3LYyYHBRSu2+pyy8GL1jTV0="
    },
    "icu": {
      "icudt_CJK.tjcz0u77k5.dat": "sha256-SZLtQnRc0JkwqHab0VUVP7T3uBPSeYzxzDnpxPpUnHk=",
      "icudt_EFIGS.tptq2av103.dat": "sha256-8fItetYY8kQ0ww6oxwTLiT3oXlBwHKumbeP2pRF4yTc=",
      "icudt_no_CJK.lfu7j35m59.dat": "sha256-L7sV7NEYP37/Qr2FPCePo5cJqRgTXRwGHuwF5Q+0Nfs="
    },
    "coreAssembly": {
      "System.Private.CoreLib.34pfvi9gnz.wasm": "sha256-48PTGN3DpnAUoTuE5AMdgI4edIc/lArdXcOAX65EPuU=",
      "System.Runtime.InteropServices.JavaScript.f4ln4hfftw.wasm": "sha256-r+LQmgoVdHgFKWJvUNAR7HQZAtSw+xvBIQ6siSPsBNM="
    },
    "assembly": {
      "BlazorApp.1d43lgvh6u.wasm": "sha256-1d2J5gSzDU8mfn5tg1xzqkYeAY03YVD23wjZtLmrvH8=",
      "Microsoft.AspNetCore.Components.n0yjlgty9j.wasm": "sha256-CQiPuKi+6NGGWAQAyuZmpSPW3jZWD4p0FqbvSH/cFKY=",
      "Microsoft.AspNetCore.Components.Web.7apenvi18o.wasm": "sha256-fyqnB2DYAO80AStwVkG2g+mFplGXI54QNWpUbk5VoiE=",
      "Microsoft.AspNetCore.Components.WebAssembly.mhi741p0i5.wasm": "sha256-pu76rHZnWXnD8OJbsfHeWNtvNYwvUMrsao8y79n+GXY=",
      "Microsoft.Extensions.Configuration.Abstractions.f9jq6u05xu.wasm": "sha256-AyL87FvJMf14Dcn8HeQ3n2veg/RQGVGCjfpJPt1RQC4=",
      "Microsoft.Extensions.Configuration.Json.77nptesqpn.wasm": "sha256-TUkUL2Leb3zmGe8ZZUHAzyb8vZoEzua1H8f8stc7xRw=",
      "Microsoft.Extensions.Configuration.ell6o7ap7i.wasm": "sha256-0iZA+rfvr3lLmK5V18g0LZCU41c3mbTL9jNYRoavdB0=",
      "Microsoft.Extensions.DependencyInjection.Abstractions.ylgtpcauec.wasm": "sha256-VoKlVeur41xeU+joJpWzatJNmvyQgP3TBlGCVdFZJbU=",
      "Microsoft.Extensions.DependencyInjection.g8opmrm9gr.wasm": "sha256-EPey4pvx6aL8aj8zL05ip1ZJSUG7DjjOrtL9aPRDYPw=",
      "Microsoft.Extensions.Logging.Abstractions.8cnp7o9mjf.wasm": "sha256-aBnl8I+SD3x3zXLX77veOrltsNcMuWifnNlGFaahme0=",
      "Microsoft.Extensions.Logging.5g1hnmwyc5.wasm": "sha256-a881iT/kmq3LnryJklnQzsMD93/W6dM0x/3xSE38e6I=",
      "Microsoft.Extensions.Options.9zsgy7ya5a.wasm": "sha256-tXQZqZqNvPMoYp2INR4AOHcvE8kWly2WAYbjvmmuiXU=",
      "Microsoft.Extensions.Primitives.8omryeirak.wasm": "sha256-iOXJ6xMILdIdSWDD2fNHtnrXI0YtuWx4chp/bwgCVgc=",
      "Microsoft.JSInterop.426305nhc4.wasm": "sha256-lNqP2ot1f2PhPr/5ZgFueuYFhUgz/pVAaqmi0u4H8Lo=",
      "Microsoft.JSInterop.WebAssembly.heoad7mujs.wasm": "sha256-99wG3VH14sWkwPaF5rX6YAcJvtAhDuqonwihvj2m5HA=",
      "System.Collections.Concurrent.hsmjajo9fw.wasm": "sha256-ITARbVistD8YETxX4DtTUovBUNej2hVaexLiO9Fimqc=",
      "System.Collections.Immutable.ouzplzmqt8.wasm": "sha256-wAL8MrgK9Q0DGs/PLBxBdBFa2bKhA40ZW6kvSyi3rUs=",
      "System.Collections.okewek4o8w.wasm": "sha256-OBDzHDPnWy6v1wbwPf/TqwLSH3yeU3auk/9qMR7g6Ic=",
      "System.ComponentModel.Primitives.dwcl0i3ajf.wasm": "sha256-c5NmfycLLD+ltahdTk2Q5+PQu4Uf40bEiJM5vyoPDl4=",
      "System.ComponentModel.TypeConverter.fnfwo5xg84.wasm": "sha256-O3NQFpf8nSRJp0/bN0iWt5qLT71WexdhgtaUKxu4gCY=",
      "System.ComponentModel.h9eo79o86x.wasm": "sha256-NQkKskUXENdTSf2C0+y41sjKi68CHmUqCgPPLNxKyGw=",
      "System.Console.ckimbfyjuj.wasm": "sha256-fG5C33jvnQc30BhFHHcR3muFlB4tfYRR2x1XYylDdrM=",
      "System.Diagnostics.DiagnosticSource.ubwvo3qscp.wasm": "sha256-lqZ7O0VKtrS6UsB/9CQe/au4pkwSW+41xR1PZMDMPiw=",
      "System.IO.Pipelines.h68d94scrb.wasm": "sha256-V5z9/XlJMVOFEDQ+R/mfLxmcykbKzh9+yhFeRdF4kdU=",
      "System.Linq.Expressions.qyb81d1kew.wasm": "sha256-kvOTEtHxxvwky+lisfkGGtChq3FCm5slBs4t9o+0zLY=",
      "System.Linq.Queryable.s5qq36zp1s.wasm": "sha256-EM4bvW0WIW38YZkrcl4F/qcY54LSEh7k5P5gFtS/dII=",
      "System.Linq.m4r18hk5bi.wasm": "sha256-lquaQ/BqcaI7U09WXneRwnYfqG2vUum+KU5NKlr9Fo8=",
      "System.Memory.acxyzgdz32.wasm": "sha256-SrBVMo6y8K0FW1a07/LPx+E73mNBQDIPA1+IPvft0aI=",
      "System.Net.Http.Json.9cqhqmryzt.wasm": "sha256-Z76MWouA0xOdZUMS1wK4Pc7OBRq+VuWERQ0jKveSpC4=",
      "System.Net.Http.qsqlx2amef.wasm": "sha256-6qNcxfIHTVoHnTqUk31hYE0IanCsN8mp2/KlnWGB9cQ=",
      "System.Net.Primitives.3uow9zd1kc.wasm": "sha256-RZU3+AurzUeBWgVjZalkA1jPlfRnehNr+R49gyYTuFI=",
      "System.ObjectModel.t8wvm8lr3b.wasm": "sha256-A0XkNdR/e3uc/rCMkN7jrsXbDHQumE49l0VO0rUEoXo=",
      "System.Private.Uri.nsfj740ux6.wasm": "sha256-t01gtK8hlN5/sZS2zCYQzCfNca/CdyMrlH0l8rT84DA=",
      "System.Runtime.dx92bx8elt.wasm": "sha256-wa3DGhcy34Jo4lKcURTmt8LnCka8XGXjpbCICzhjNdc=",
      "System.Text.Encodings.Web.4zpcd8unrt.wasm": "sha256-gAQK1aO5MWD0GwIAc812qHpnec5wlHwgnyaZ9RGOUOg=",
      "System.Text.Json.qgii1bka67.wasm": "sha256-BmVGX8/VAA7rb0CMvelfXRRcVlaIwI1mHP1fwAdVrms=",
      "System.Text.RegularExpressions.0e9rlv7vxy.wasm": "sha256-SKkTQL9D0Loskr+NX705/WITcRNb/8VQlQorMrz5S6M=",
      "System.v3da086c8u.wasm": "sha256-JR9uHwZeWzGLHbZhs4tvobv0QX0mykH6Dw/KbNqFbCA="
    }
  },
  "cacheBootResources": true,
  "debugLevel": 0,
  "linkerEnabled": true,
  "globalizationMode": "sharded",
  "extensions": {
    "blazor": {}
  }
}